markup_ai/__init__.py
markup_ai/client.py
markup_ai/core/__init__.py
markup_ai/core/api_error.py
markup_ai/core/client_wrapper.py
markup_ai/core/datetime_utils.py
markup_ai/core/file.py
markup_ai/core/force_multipart.py
markup_ai/core/http_client.py
markup_ai/core/http_response.py
markup_ai/core/jsonable_encoder.py
markup_ai/core/pydantic_utilities.py
markup_ai/core/query_encoder.py
markup_ai/core/remove_none_from_dict.py
markup_ai/core/request_options.py
markup_ai/core/serialization.py
markup_ai/environment.py
markup_ai/errors/__init__.py
markup_ai/errors/conflict_error.py
markup_ai/errors/content_too_large_error.py
markup_ai/errors/forbidden_error.py
markup_ai/errors/internal_server_error.py
markup_ai/errors/not_found_error.py
markup_ai/errors/too_many_requests_error.py
markup_ai/errors/unauthorized_error.py
markup_ai/errors/unprocessable_entity_error.py
markup_ai/py.typed
markup_ai/style_checks/__init__.py
markup_ai/style_checks/client.py
markup_ai/style_checks/raw_client.py
markup_ai/style_guides/__init__.py
markup_ai/style_guides/client.py
markup_ai/style_guides/raw_client.py
markup_ai/style_rewrites/__init__.py
markup_ai/style_rewrites/client.py
markup_ai/style_rewrites/raw_client.py
markup_ai/style_suggestions/__init__.py
markup_ai/style_suggestions/client.py
markup_ai/style_suggestions/raw_client.py
markup_ai/terminology/__init__.py
markup_ai/terminology/client.py
markup_ai/terminology/raw_client.py
markup_ai/types/__init__.py
markup_ai/types/analysis_score.py
markup_ai/types/base_style_guide_type.py
markup_ai/types/clarity_category.py
markup_ai/types/clarity_score.py
markup_ai/types/config_options.py
markup_ai/types/consistency_category.py
markup_ai/types/consistency_score.py
markup_ai/types/dialects.py
markup_ai/types/domain_response.py
markup_ai/types/domain_summary.py
markup_ai/types/error_response.py
markup_ai/types/grammar_category.py
markup_ai/types/grammar_score.py
markup_ai/types/import_summary.py
markup_ai/types/issue.py
markup_ai_api-1.5.0.dist-info/LICENSE
markup_ai_api-1.5.0.dist-info/METADATA
markup_ai_api-1.5.0.dist-info/WHEEL
markup_ai_api-1.5.0.dist-info/RECORD
